Shift_register_8bit/design.sv
module shift_register_8bit (
    input  logic        clk,
    input  logic        rst_n,
    input  logic        shift_enable,
    input  logic        data_in,
    output logic [7:0]  data_out
);
    always_ff @(posedge clk or negedge rst_n) begin
        if (!rst_n)
            data_out <= 8'b0;
        else if (shift_enable)
            data_out <= {data_out[6:0], data_in};
    end
endmodule

Shift_register_8bit/testbench.sv
module shift_reg_tb;
    logic clk;
    logic rst_n;
    logic shift_enable;
    logic data_in;
    logic [7:0] data_out;

    shift_register_8bit dut (
        .clk(clk),
        .rst_n(rst_n),
        .shift_enable(shift_enable),
        .data_in(data_in),
        .data_out(data_out)
    );

    initial begin
        $dumpfile("dump.vcd");
      $dumpvars(0,shift_reg_tb);
        clk = 0;
        forever #5 clk = ~clk;
    end

    initial begin
        rst_n = 0;
        shift_enable = 0;
        data_in = 0;
        #15 rst_n = 1;
    end

    initial begin
        @(posedge rst_n);
        shift_enable = 1;
        data_in = 1'b1;
        #10;
        data_in = 1'b0;
        #10;
        data_in = 1'b1;
        #10;
        data_in = 1'b1;
        #10;
        data_in = 1'b0;
        #10;
        data_in = 1'b1;
        #10;
        data_in = 1'b0;
        #10;
        data_in = 1'b1;
        #10;
        shift_enable = 0;
        #10;
        $finish;
    end
endmodule

Shift_register_8bit/dump.vcd
$date
	Sun Oct 20 03:37:38 2024
$end
$version
	QuestaSim Version 2023.1
$end
$timescale
	1ns
$end

$scope module shift_reg_tb $end
$var reg 1 ! clk $end
$var reg 1 " data_in $end
$var reg 8 # data_out [7:0] $end
$var reg 1 $ rst_n $end
$var reg 1 % shift_enable $end

$scope module dut $end
$var wire 1 & clk $end
$var wire 1 ' data_in $end
$var wire 1 ( rst_n $end
$var wire 1 ) shift_enable $end
$var reg 8 * data_out [7:0] $end
$upscope $end
$upscope $end
$enddefinitions $end
#0
$dumpvars
0'
0)
0(
0&
0!
0"
b0 #
0$
0%
b0 *
$end
#5
1!
1&
#10
0!
0&
#15
1$
1!
1(
1&
1%
1"
1)
1'
#20
0!
0&
#25
0"
1!
0'
1&
#30
0!
0&
#35
1"
1!
1'
1&
b1 *
b1 #
#40
0!
0&
#45
1!
1&
b11 *
b11 #
#50
0!
0&
#55
0"
1!
0'
1&
b110 *
b110 #
#60
0!
0&
#65
1"
1!
1'
1&
b1101 *
b1101 #
#70
0!
0&
#75
0"
1!
0'
1&
b11010 *
b11010 #
#80
0!
0&
#85
1"
1!
1'
1&
b110101 *
b110101 #
#90
0!
0&
#95
0%
1!
0)
1&
